jjaeseo_ensemble/__init__.py
jjaeseo_ensemble/ensemble_module.py
jjaeseo_ensenble-0.0.1.dist-info/LICENSE.txt
jjaeseo_ensenble-0.0.1.dist-info/METADATA
jjaeseo_ensenble-0.0.1.dist-info/WHEEL
jjaeseo_ensenble-0.0.1.dist-info/top_level.txt
jjaeseo_ensenble-0.0.1.dist-info/RECORD
