Metadata-Version: 2.1
Name: jjaeseo-ensenble
Version: 0.0.1
Summary: Machine Learning Week7 Ensenble Model Making Practice
Home-page: https://github.com/JJaeseo
Author: jjaeseo
Author-email: js.chong220@gmail.com
Classifier: Programming Language :: Python :: 3
Classifier: License :: OSI Approved :: MIT License
Classifier: Operating System :: OS Independent
Requires-Python: >=3.10
License-File: LICENSE.txt
